AndroidSdkJiaocheng/README.md
AndroidSdkJiaocheng/__init__.py
AndroidSdkJiaocheng/__main__.py
AndroidSdkJiaocheng/file.epub
AndroidSdkJiaocheng/index.html
AndroidSdkJiaocheng/css/__init__.py
AndroidSdkJiaocheng/css/annotations.css
AndroidSdkJiaocheng/css/main.css
AndroidSdkJiaocheng/css/normalize.css
AndroidSdkJiaocheng/css/popup.css
AndroidSdkJiaocheng/font/__init__.py
AndroidSdkJiaocheng/font/fontello.eot
AndroidSdkJiaocheng/font/fontello.svg
AndroidSdkJiaocheng/font/fontello.ttf
AndroidSdkJiaocheng/font/fontello.woff
AndroidSdkJiaocheng/img/__init__.py
AndroidSdkJiaocheng/img/annotator-glyph-sprite.png
AndroidSdkJiaocheng/img/annotator-icon-sprite.png
AndroidSdkJiaocheng/img/apple-touch-icon.png
AndroidSdkJiaocheng/img/cancelfullscreen.png
AndroidSdkJiaocheng/img/close.png
AndroidSdkJiaocheng/img/fullscreen.png
AndroidSdkJiaocheng/img/loader.gif
AndroidSdkJiaocheng/img/menu-icon.png
AndroidSdkJiaocheng/img/save.png
AndroidSdkJiaocheng/img/saved.png
AndroidSdkJiaocheng/img/settings-s.png
AndroidSdkJiaocheng/img/settings.png
AndroidSdkJiaocheng/img/star.png
AndroidSdkJiaocheng/js/__init__.py
AndroidSdkJiaocheng/js/epub.js
AndroidSdkJiaocheng/js/epub.min.js
AndroidSdkJiaocheng/js/epub.min.map
AndroidSdkJiaocheng/js/hooks.min.js
AndroidSdkJiaocheng/js/hooks.min.map
AndroidSdkJiaocheng/js/reader.js
AndroidSdkJiaocheng/js/reader.js.map
AndroidSdkJiaocheng/js/reader.min.js
AndroidSdkJiaocheng/js/reader.min.map
AndroidSdkJiaocheng/js/hooks/__init__.py
AndroidSdkJiaocheng/js/hooks/extensions/__init__.py
AndroidSdkJiaocheng/js/hooks/extensions/highlight.js
AndroidSdkJiaocheng/js/libs/__init__.py
AndroidSdkJiaocheng/js/libs/jquery.min.js
AndroidSdkJiaocheng/js/libs/localforage.min.js
AndroidSdkJiaocheng/js/libs/screenfull.js
AndroidSdkJiaocheng/js/libs/screenfull.min.js
AndroidSdkJiaocheng/js/libs/zip.min.js
AndroidSdkJiaocheng/js/plugins/__init__.py
AndroidSdkJiaocheng/js/plugins/hypothesis.js
AndroidSdkJiaocheng/js/plugins/search.js
android_sdk_jiaocheng-2024.3.3.0.dist-info/METADATA
android_sdk_jiaocheng-2024.3.3.0.dist-info/WHEEL
android_sdk_jiaocheng-2024.3.3.0.dist-info/entry_points.txt
android_sdk_jiaocheng-2024.3.3.0.dist-info/top_level.txt
android_sdk_jiaocheng-2024.3.3.0.dist-info/RECORD
